cutgeneratingfunctionology/__init__.py
cutgeneratingfunctionology/dff/Gomory_conversion.sage
cutgeneratingfunctionology/dff/__init__.py
cutgeneratingfunctionology/dff/computer_based_search_naive_dff.sage
cutgeneratingfunctionology/dff/dff_functions.sage
cutgeneratingfunctionology/dff/dff_test_plot.sage
cutgeneratingfunctionology/dff/discontinuous_dff.sage
cutgeneratingfunctionology/dff/gdff_linear_test.sage
cutgeneratingfunctionology/igp/2q_mip.sage
cutgeneratingfunctionology/igp/__init__.py
cutgeneratingfunctionology/igp/animation_2d_diagram.sage
cutgeneratingfunctionology/igp/bug_examples.sage
cutgeneratingfunctionology/igp/class_call.py
cutgeneratingfunctionology/igp/compendium_procedures.sage
cutgeneratingfunctionology/igp/continuous_case.sage
cutgeneratingfunctionology/igp/crazy_perturbation.sage
cutgeneratingfunctionology/igp/crazy_perturbation_examples.sage
cutgeneratingfunctionology/igp/discontinuous_case.sage
cutgeneratingfunctionology/igp/discrete_case.sage
cutgeneratingfunctionology/igp/extreme_functions.py
cutgeneratingfunctionology/igp/extreme_functions_in_literature.sage
cutgeneratingfunctionology/igp/extreme_functions_mlr_cpl3.sage
cutgeneratingfunctionology/igp/extreme_functions_sporadic.sage
cutgeneratingfunctionology/igp/fast_linear.py
cutgeneratingfunctionology/igp/fast_piecewise.py
cutgeneratingfunctionology/igp/faster_subadditivity_test.sage
cutgeneratingfunctionology/igp/faster_subadditivity_test_discontinuous.sage
cutgeneratingfunctionology/igp/functions.sage
cutgeneratingfunctionology/igp/intervals.py
cutgeneratingfunctionology/igp/kslope_mip.sage
cutgeneratingfunctionology/igp/kslope_pattern.sage
cutgeneratingfunctionology/igp/kslope_ppl_mip.py
cutgeneratingfunctionology/igp/lifting_project.sage
cutgeneratingfunctionology/igp/logging.sage
cutgeneratingfunctionology/igp/move_semigroup.py
cutgeneratingfunctionology/igp/parametric.sage
cutgeneratingfunctionology/igp/parametric_cpl.sage
cutgeneratingfunctionology/igp/parametric_family.py
cutgeneratingfunctionology-1.5.4.dist-info/licenses/AUTHORS.rst
cutgeneratingfunctionology-1.5.4.dist-info/licenses/COPYING
cutgeneratingfunctionology-1.5.4.dist-info/METADATA
cutgeneratingfunctionology-1.5.4.dist-info/WHEEL
cutgeneratingfunctionology-1.5.4.dist-info/top_level.txt
cutgeneratingfunctionology-1.5.4.dist-info/RECORD
