Metadata-Version: 2.4
Name: cutgeneratingfunctionology
Version: 1.5.4
Summary: Python code for computation and experimentation with cut-generating functions
Author: Yuan Zhou, Chun Yu Hong, Jiawei Wang, with contributions by undergraduate programmers
Author-email: Matthias Koeppe <mkoeppe@math.ucdavis.edu>
License-Expression: GPL-2.0-or-later
Project-URL: Homepage, https://github.com/mkoeppe/cutgeneratingfunctionology
Project-URL: Documentation, http://mkoeppe.github.io/cutgeneratingfunctionology/doc/html/
Project-URL: Source, https://github.com/mkoeppe/cutgeneratingfunctionology
Project-URL: Issue Tracker, https://github.com/mkoeppe/cutgeneratingfunctionology/issues
Project-URL: Demo on mybinder.org, https://mybinder.org/v2/gh/mkoeppe/cutgeneratingfunctionology/master?filepath=demo.ipynb
Keywords: integer programming,cutting planes
Classifier: Development Status :: 5 - Production/Stable
Classifier: Intended Audience :: Science/Research
Classifier: Programming Language :: Python
Classifier: Programming Language :: Python :: 3
Classifier: Programming Language :: Python :: 3.9
Classifier: Programming Language :: Python :: 3.10
Classifier: Programming Language :: Python :: 3.11
Classifier: Programming Language :: Python :: 3.12
Classifier: Programming Language :: Python :: 3.13
Classifier: Topic :: Scientific/Engineering :: Mathematics
Requires-Python: >=3.9
License-File: COPYING
License-File: AUTHORS.rst
Provides-Extra: doc
Requires-Dist: cutgeneratingfunctionology[passagemath]; extra == "doc"
Requires-Dist: sage-package; extra == "doc"
Requires-Dist: sphinx; extra == "doc"
Requires-Dist: sphinxcontrib-bibtex; extra == "doc"
Provides-Extra: passagemath
Requires-Dist: passagemath-pari; extra == "passagemath"
Requires-Dist: passagemath-polyhedra; extra == "passagemath"
Requires-Dist: passagemath-plot; extra == "passagemath"
Requires-Dist: passagemath-repl; extra == "passagemath"
Requires-Dist: passagemath-flint; extra == "passagemath"
Requires-Dist: passagemath-graphs; extra == "passagemath"
Requires-Dist: passagemath-singular; extra == "passagemath"
Requires-Dist: passagemath-symbolics; extra == "passagemath"
Dynamic: license-file
